{
  "summary": "Two Democratic members of Congress, Maxwell Frost and Ilhan Omar, were recently accosted in separate incidents. Frost was allegedly attacked by an assailant who punched him and made racist remarks, while Omar was interrupted by a man at a town hall in Minneapolis. Both incidents have raised concerns about the safety and security of elected officials. The incidents have also sparked a reaction from President Donald Trump, who made controversial comments about Omar. The president's response has been criticized for being insensitive and conspiratorial. The incidents highlight the need for increased security measures to protect members of Congress. The U.S. Capitol Police have announced that they are working with federal partners to investigate the incidents and bring the perpetrators to justice.",
  "bias_scores": {
    "Left": 0.7,
    "Center": 0.2,
    "Right": 0.1
  },
  "top_signal": "Incidents of violence against members of Congress",
  "essay": "The recent incidents of violence against members of Congress are a cause for concern. The attacks on Maxwell Frost and Ilhan Omar are a reminder that elected officials are not immune to violence and harassment. The incidents have sparked a debate about the need for increased security measures to protect members of Congress. The U.S. Capitol Police have announced that they are working with federal partners to investigate the incidents and bring the perpetrators to justice. The incidents have also raised questions about the role of rhetoric and discourse in contributing to a culture of violence and intolerance. The response of President Donald Trump to the incidents has been criticized for being insensitive and conspiratorial. The president's comments have been seen as a reflection of a broader problem of divisive rhetoric and polarization in American politics. The incidents highlight the need for a more civil and respectful discourse in American politics. The safety and security of elected officials must be a priority, and all Americans must work together to create a culture of respect and tolerance."
}